{
  "name": "TCGA-06-0221-01Z-00-DX1.bc444e2a-9530-453a-b494-ec31ee5db9c1.svs",
  "all_detections": [
    {
      "name": "31_19.jpeg",
      "detections": [
        [
          "atypical",
          0.5568971037864685,
          [
            683,
            571,
            26,
            26
          ]
        ]
      ]
    },
    {
      "name": "34_16.jpeg",
      "detections": [
        [
          "normal",
          0.5063012838363647,
          [
            425,
            311,
            31,
            36
          ]
        ]
      ]
    },
    {
      "name": "3_12.jpeg",
      "detections": [
        [
          "normal",
          0.6018543243408203,
          [
            539,
            200,
            14,
            23
          ]
        ]
      ]
    },
    {
      "name": "25_18.jpeg",
      "detections": [
        [
          "normal",
          0.6257005929946899,
          [
            344,
            292,
            18,
            16
          ]
        ]
      ]
    },
    {
      "name": "33_7.jpeg",
      "detections": [
        [
          "atypical",
          0.5026454925537109,
          [
            362,
            556,
            22,
            20
          ]
        ]
      ]
    },
    {
      "name": "38_11.jpeg",
      "detections": [
        [
          "normal",
          0.597968339920044,
          [
            228,
            580,
            51,
            28
          ]
        ]
      ]
    },
    {
      "name": "34_5.jpeg",
      "detections": [
        [
          "normal",
          0.5976378917694092,
          [
            445,
            678,
            33,
            44
          ]
        ]
      ]
    },
    {
      "name": "36_8.jpeg",
      "detections": [
        [
          "normal",
          0.6400307416915894,
          [
            168,
            28,
            31,
            30
          ]
        ],
        [
          "normal",
          0.5952044725418091,
          [
            148,
            276,
            16,
            26
          ]
        ]
      ]
    },
    {
      "name": "36_9.jpeg",
      "detections": [
        [
          "normal",
          0.5852110981941223,
          [
            21,
            35,
            31,
            57
          ]
        ]
      ]
    },
    {
      "name": "13_7.jpeg",
      "detections": [
        [
          "normal",
          0.7134436964988708,
          [
            136,
            387,
            25,
            20
          ]
        ]
      ]
    },
    {
      "name": "37_11.jpeg",
      "detections": [
        [
          "normal",
          0.6262996196746826,
          [
            712,
            440,
            19,
            20
          ]
        ]
      ]
    },
    {
      "name": "37_16.jpeg",
      "detections": [
        [
          "granular",
          0.5920206308364868,
          [
            28,
            613,
            54,
            49
          ]
        ]
      ]
    },
    {
      "name": "2_11.jpeg",
      "detections": [
        [
          "normal",
          0.6161043047904968,
          [
            83,
            199,
            25,
            26
          ]
        ]
      ]
    },
    {
      "name": "8_16.jpeg",
      "detections": [
        [
          "normal",
          0.5994324684143066,
          [
            338,
            313,
            19,
            23
          ]
        ]
      ]
    },
    {
      "name": "3_6.jpeg",
      "detections": [
        [
          "atypical",
          0.666279673576355,
          [
            0,
            465,
            29,
            37
          ]
        ]
      ]
    },
    {
      "name": "3_11.jpeg",
      "detections": [
        [
          "normal",
          0.5651789903640747,
          [
            591,
            497,
            21,
            20
          ]
        ]
      ]
    },
    {
      "name": "9_15.jpeg",
      "detections": [
        [
          "normal",
          0.5502628087997437,
          [
            78,
            656,
            19,
            22
          ]
        ]
      ]
    },
    {
      "name": "6_7.jpeg",
      "detections": [
        [
          "normal",
          0.5356625318527222,
          [
            99,
            191,
            22,
            28
          ]
        ]
      ]
    },
    {
      "name": "7_17.jpeg",
      "detections": [
        [
          "atypical",
          0.6656792759895325,
          [
            312,
            0,
            35,
            37
          ]
        ]
      ]
    },
    {
      "name": "9_7.jpeg",
      "detections": [
        [
          "normal",
          0.5506267547607422,
          [
            398,
            681,
            22,
            17
          ]
        ]
      ]
    },
    {
      "name": "9_13.jpeg",
      "detections": [
        [
          "normal",
          0.557340681552887,
          [
            191,
            382,
            19,
            23
          ]
        ],
        [
          "normal",
          0.5409030318260193,
          [
            68,
            181,
            22,
            21
          ]
        ]
      ]
    },
    {
      "name": "28_11.jpeg",
      "detections": [
        [
          "normal",
          0.7484803199768066,
          [
            741,
            431,
            27,
            18
          ]
        ]
      ]
    },
    {
      "name": "30_10.jpeg",
      "detections": [
        [
          "normal",
          0.7106789350509644,
          [
            510,
            240,
            29,
            31
          ]
        ],
        [
          "normal",
          0.5467112064361572,
          [
            656,
            326,
            28,
            25
          ]
        ]
      ]
    },
    {
      "name": "36_10.jpeg",
      "detections": [
        [
          "normal",
          0.5606316328048706,
          [
            4,
            720,
            35,
            33
          ]
        ]
      ]
    },
    {
      "name": "32_16.jpeg",
      "detections": [
        [
          "normal",
          0.6363164186477661,
          [
            640,
            640,
            20,
            19
          ]
        ]
      ]
    },
    {
      "name": "29_10.jpeg",
      "detections": [
        [
          "normal",
          0.682846188545227,
          [
            2,
            774,
            27,
            21
          ]
        ]
      ]
    },
    {
      "name": "12_10.jpeg",
      "detections": [
        [
          "normal",
          0.7307601571083069,
          [
            172,
            513,
            23,
            16
          ]
        ]
      ]
    },
    {
      "name": "39_13.jpeg",
      "detections": [
        [
          "normal",
          0.5279226303100586,
          [
            71,
            290,
            15,
            18
          ]
        ]
      ]
    },
    {
      "name": "36_11.jpeg",
      "detections": [
        [
          "normal",
          0.7171987891197205,
          [
            435,
            25,
            41,
            39
          ]
        ],
        [
          "normal",
          0.7106882929801941,
          [
            104,
            351,
            38,
            38
          ]
        ],
        [
          "normal",
          0.5365014672279358,
          [
            45,
            27,
            24,
            34
          ]
        ]
      ]
    },
    {
      "name": "35_11.jpeg",
      "detections": [
        [
          "normal",
          0.5121052265167236,
          [
            644,
            185,
            38,
            31
          ]
        ]
      ]
    },
    {
      "name": "9_18.jpeg",
      "detections": [
        [
          "normal",
          0.6212283372879028,
          [
            220,
            407,
            27,
            29
          ]
        ]
      ]
    },
    {
      "name": "29_13.jpeg",
      "detections": [
        [
          "normal",
          0.7432719469070435,
          [
            131,
            492,
            43,
            48
          ]
        ]
      ]
    },
    {
      "name": "37_10.jpeg",
      "detections": [
        [
          "normal",
          0.6131727695465088,
          [
            730,
            254,
            28,
            17
          ]
        ]
      ]
    },
    {
      "name": "32_7.jpeg",
      "detections": [
        [
          "atypical",
          0.7161484360694885,
          [
            485,
            739,
            23,
            23
          ]
        ]
      ]
    },
    {
      "name": "35_9.jpeg",
      "detections": [
        [
          "normal",
          0.6601830720901489,
          [
            223,
            276,
            25,
            15
          ]
        ],
        [
          "normal",
          0.5845625400543213,
          [
            701,
            113,
            24,
            31
          ]
        ],
        [
          "normal",
          0.5807092189788818,
          [
            695,
            367,
            40,
            31
          ]
        ],
        [
          "normal",
          0.5404274463653564,
          [
            35,
            340,
            18,
            33
          ]
        ],
        [
          "normal",
          0.5237143635749817,
          [
            655,
            277,
            24,
            41
          ]
        ]
      ]
    },
    {
      "name": "6_10.jpeg",
      "detections": [
        [
          "normal",
          0.5585988163948059,
          [
            191,
            382,
            20,
            19
          ]
        ]
      ]
    },
    {
      "name": "35_8.jpeg",
      "detections": [
        [
          "normal",
          0.6568133234977722,
          [
            270,
            741,
            44,
            35
          ]
        ]
      ]
    },
    {
      "name": "31_5.jpeg",
      "detections": [
        [
          "normal",
          0.7219523191452026,
          [
            118,
            186,
            30,
            36
          ]
        ]
      ]
    },
    {
      "name": "2_10.jpeg",
      "detections": [
        [
          "normal",
          0.5399823784828186,
          [
            737,
            596,
            25,
            25
          ]
        ]
      ]
    },
    {
      "name": "9_14.jpeg",
      "detections": [
        [
          "normal",
          0.5513050556182861,
          [
            223,
            93,
            14,
            26
          ]
        ]
      ]
    },
    {
      "name": "5_12.jpeg",
      "detections": [
        [
          "normal",
          0.6616959571838379,
          [
            452,
            32,
            27,
            26
          ]
        ]
      ]
    },
    {
      "name": "33_20.jpeg",
      "detections": [
        [
          "normal",
          0.6392633318901062,
          [
            730,
            736,
            45,
            33
          ]
        ]
      ]
    },
    {
      "name": "40_16.jpeg",
      "detections": [
        [
          "normal",
          0.5517423748970032,
          [
            173,
            123,
            16,
            34
          ]
        ]
      ]
    },
    {
      "name": "30_9.jpeg",
      "detections": [
        [
          "normal",
          0.5830155611038208,
          [
            522,
            408,
            21,
            23
          ]
        ]
      ]
    },
    {
      "name": "3_7.jpeg",
      "detections": [
        [
          "normal",
          0.576119065284729,
          [
            417,
            68,
            22,
            26
          ]
        ]
      ]
    },
    {
      "name": "7_10.jpeg",
      "detections": [
        [
          "normal",
          0.7226837277412415,
          [
            646,
            140,
            22,
            25
          ]
        ]
      ]
    }
  ]
}