{
  "name": "TCGA-06-0219-01Z-00-DX1.592a9605-e9ec-46f5-a055-5001088f47d0.svs",
  "all_detections": [
    {
      "name": "29_24.jpeg",
      "detections": [
        [
          "normal",
          0.7101746797561646,
          [
            490,
            240,
            68,
            82
          ]
        ]
      ]
    },
    {
      "name": "23_12.jpeg",
      "detections": [
        [
          "normal",
          0.5853270888328552,
          [
            657,
            695,
            52,
            63
          ]
        ]
      ]
    },
    {
      "name": "34_16.jpeg",
      "detections": [
        [
          "normal",
          0.5458498597145081,
          [
            110,
            360,
            103,
            110
          ]
        ]
      ]
    },
    {
      "name": "31_18.jpeg",
      "detections": [
        [
          "normal",
          0.6221381425857544,
          [
            716,
            385,
            16,
            24
          ]
        ]
      ]
    },
    {
      "name": "30_19.jpeg",
      "detections": [
        [
          "normal",
          0.5341566801071167,
          [
            373,
            286,
            26,
            30
          ]
        ]
      ]
    },
    {
      "name": "74_12.jpeg",
      "detections": [
        [
          "normal",
          0.5487672686576843,
          [
            524,
            694,
            101,
            80
          ]
        ]
      ]
    },
    {
      "name": "80_19.jpeg",
      "detections": [
        [
          "normal",
          0.6657565832138062,
          [
            604,
            4,
            46,
            55
          ]
        ]
      ]
    },
    {
      "name": "43_15.jpeg",
      "detections": [
        [
          "atypical",
          0.5407995581626892,
          [
            518,
            629,
            43,
            56
          ]
        ]
      ]
    },
    {
      "name": "63_3.jpeg",
      "detections": [
        [
          "normal",
          0.5009512901306152,
          [
            695,
            551,
            14,
            18
          ]
        ]
      ]
    },
    {
      "name": "5_19.jpeg",
      "detections": [
        [
          "normal",
          0.6905815005302429,
          [
            482,
            472,
            15,
            16
          ]
        ]
      ]
    },
    {
      "name": "3_19.jpeg",
      "detections": [
        [
          "normal",
          0.5138331055641174,
          [
            237,
            486,
            15,
            24
          ]
        ]
      ]
    },
    {
      "name": "36_20.jpeg",
      "detections": [
        [
          "normal",
          0.6217347383499146,
          [
            293,
            303,
            35,
            25
          ]
        ]
      ]
    },
    {
      "name": "21_15.jpeg",
      "detections": [
        [
          "normal",
          0.5437676310539246,
          [
            543,
            559,
            51,
            60
          ]
        ]
      ]
    },
    {
      "name": "33_18.jpeg",
      "detections": [
        [
          "normal",
          0.6682211756706238,
          [
            627,
            167,
            42,
            36
          ]
        ]
      ]
    },
    {
      "name": "18_24.jpeg",
      "detections": [
        [
          "normal",
          0.5916174650192261,
          [
            479,
            109,
            23,
            25
          ]
        ]
      ]
    },
    {
      "name": "71_20.jpeg",
      "detections": [
        [
          "normal",
          0.5526272058486938,
          [
            420,
            14,
            22,
            26
          ]
        ]
      ]
    },
    {
      "name": "53_19.jpeg",
      "detections": [
        [
          "normal",
          0.702298641204834,
          [
            671,
            517,
            24,
            24
          ]
        ],
        [
          "normal",
          0.67449551820755,
          [
            381,
            481,
            23,
            18
          ]
        ],
        [
          "atypical",
          0.6066113114356995,
          [
            92,
            430,
            25,
            28
          ]
        ],
        [
          "normal",
          0.5154420137405396,
          [
            599,
            365,
            20,
            17
          ]
        ]
      ]
    },
    {
      "name": "68_22.jpeg",
      "detections": [
        [
          "atypical",
          0.6493958234786987,
          [
            364,
            73,
            19,
            19
          ]
        ]
      ]
    },
    {
      "name": "4_19.jpeg",
      "detections": [
        [
          "atypical",
          0.6004441976547241,
          [
            559,
            77,
            28,
            37
          ]
        ]
      ]
    },
    {
      "name": "78_16.jpeg",
      "detections": [
        [
          "normal",
          0.5957351326942444,
          [
            713,
            399,
            26,
            20
          ]
        ]
      ]
    },
    {
      "name": "53_18.jpeg",
      "detections": [
        [
          "normal",
          0.7022784352302551,
          [
            719,
            156,
            47,
            38
          ]
        ],
        [
          "normal",
          0.6111342906951904,
          [
            620,
            721,
            92,
            67
          ]
        ],
        [
          "normal",
          0.538524866104126,
          [
            13,
            553,
            16,
            19
          ]
        ],
        [
          "normal",
          0.5327724814414978,
          [
            470,
            390,
            15,
            19
          ]
        ]
      ]
    },
    {
      "name": "19_24.jpeg",
      "detections": [
        [
          "normal",
          0.5110341310501099,
          [
            572,
            170,
            30,
            48
          ]
        ]
      ]
    },
    {
      "name": "32_18.jpeg",
      "detections": [
        [
          "normal",
          0.7110655903816223,
          [
            337,
            608,
            36,
            34
          ]
        ],
        [
          "normal",
          0.63664311170578,
          [
            164,
            745,
            40,
            52
          ]
        ]
      ]
    },
    {
      "name": "23_24.jpeg",
      "detections": [
        [
          "normal",
          0.5091122984886169,
          [
            311,
            349,
            13,
            19
          ]
        ]
      ]
    },
    {
      "name": "19_18.jpeg",
      "detections": [
        [
          "granular",
          0.7106890678405762,
          [
            655,
            20,
            46,
            63
          ]
        ]
      ]
    },
    {
      "name": "2_19.jpeg",
      "detections": [
        [
          "normal",
          0.6642017960548401,
          [
            290,
            4,
            22,
            20
          ]
        ]
      ]
    },
    {
      "name": "28_16.jpeg",
      "detections": [
        [
          "normal",
          0.540424108505249,
          [
            288,
            536,
            36,
            27
          ]
        ]
      ]
    },
    {
      "name": "20_18.jpeg",
      "detections": [
        [
          "normal",
          0.5786497592926025,
          [
            276,
            155,
            34,
            26
          ]
        ]
      ]
    },
    {
      "name": "50_18.jpeg",
      "detections": [
        [
          "normal",
          0.6043373346328735,
          [
            233,
            544,
            28,
            27
          ]
        ]
      ]
    },
    {
      "name": "8_23.jpeg",
      "detections": [
        [
          "normal",
          0.5560827255249023,
          [
            321,
            191,
            16,
            20
          ]
        ]
      ]
    },
    {
      "name": "75_18.jpeg",
      "detections": [
        [
          "normal",
          0.5385021567344666,
          [
            422,
            557,
            41,
            47
          ]
        ]
      ]
    },
    {
      "name": "52_27.jpeg",
      "detections": [
        [
          "normal",
          0.574178159236908,
          [
            184,
            53,
            41,
            59
          ]
        ]
      ]
    },
    {
      "name": "22_20.jpeg",
      "detections": [
        [
          "normal",
          0.6155558228492737,
          [
            485,
            781,
            31,
            19
          ]
        ]
      ]
    },
    {
      "name": "56_21.jpeg",
      "detections": [
        [
          "normal",
          0.653164267539978,
          [
            327,
            120,
            18,
            23
          ]
        ]
      ]
    },
    {
      "name": "13_9.jpeg",
      "detections": [
        [
          "normal",
          0.7213241457939148,
          [
            668,
            465,
            39,
            25
          ]
        ]
      ]
    },
    {
      "name": "13_19.jpeg",
      "detections": [
        [
          "atypical",
          0.5003137588500977,
          [
            783,
            718,
            16,
            30
          ]
        ]
      ]
    },
    {
      "name": "62_24.jpeg",
      "detections": [
        [
          "normal",
          0.5257619023323059,
          [
            189,
            93,
            14,
            18
          ]
        ]
      ]
    },
    {
      "name": "24_20.jpeg",
      "detections": [
        [
          "normal",
          0.6859785914421082,
          [
            662,
            371,
            30,
            18
          ]
        ]
      ]
    },
    {
      "name": "30_18.jpeg",
      "detections": [
        [
          "normal",
          0.6662508249282837,
          [
            109,
            413,
            23,
            19
          ]
        ]
      ]
    },
    {
      "name": "13_18.jpeg",
      "detections": [
        [
          "normal",
          0.6452118158340454,
          [
            267,
            213,
            20,
            29
          ]
        ]
      ]
    },
    {
      "name": "18_16.jpeg",
      "detections": [
        [
          "normal",
          0.606419026851654,
          [
            708,
            764,
            35,
            30
          ]
        ]
      ]
    },
    {
      "name": "16_11.jpeg",
      "detections": [
        [
          "normal",
          0.6540952920913696,
          [
            0,
            420,
            56,
            64
          ]
        ]
      ]
    },
    {
      "name": "9_19.jpeg",
      "detections": [
        [
          "normal",
          0.5658078789710999,
          [
            212,
            279,
            23,
            25
          ]
        ]
      ]
    },
    {
      "name": "23_25.jpeg",
      "detections": [
        [
          "normal",
          0.7065140604972839,
          [
            92,
            315,
            33,
            37
          ]
        ]
      ]
    },
    {
      "name": "17_16.jpeg",
      "detections": [
        [
          "normal",
          0.6551701426506042,
          [
            353,
            747,
            17,
            18
          ]
        ]
      ]
    },
    {
      "name": "76_14.jpeg",
      "detections": [
        [
          "normal",
          0.5850353837013245,
          [
            739,
            260,
            43,
            52
          ]
        ]
      ]
    },
    {
      "name": "74_19.jpeg",
      "detections": [
        [
          "normal",
          0.5315176248550415,
          [
            255,
            590,
            36,
            29
          ]
        ]
      ]
    },
    {
      "name": "52_18.jpeg",
      "detections": [
        [
          "normal",
          0.6335291862487793,
          [
            456,
            0,
            40,
            22
          ]
        ]
      ]
    },
    {
      "name": "11_24.jpeg",
      "detections": [
        [
          "atypical",
          0.724203884601593,
          [
            129,
            8,
            20,
            23
          ]
        ]
      ]
    },
    {
      "name": "54_19.jpeg",
      "detections": [
        [
          "granular",
          0.6477392315864563,
          [
            248,
            472,
            40,
            45
          ]
        ]
      ]
    },
    {
      "name": "69_22.jpeg",
      "detections": [
        [
          "atypical",
          0.6026851534843445,
          [
            56,
            690,
            21,
            22
          ]
        ]
      ]
    },
    {
      "name": "51_20.jpeg",
      "detections": [
        [
          "atypical",
          0.5264834761619568,
          [
            659,
            728,
            22,
            18
          ]
        ],
        [
          "granular",
          0.5079310536384583,
          [
            662,
            226,
            31,
            38
          ]
        ]
      ]
    },
    {
      "name": "9_21.jpeg",
      "detections": [
        [
          "normal",
          0.7159358859062195,
          [
            261,
            228,
            21,
            18
          ]
        ],
        [
          "normal",
          0.6647875308990479,
          [
            51,
            311,
            23,
            18
          ]
        ]
      ]
    },
    {
      "name": "10_22.jpeg",
      "detections": [
        [
          "normal",
          0.6206514835357666,
          [
            579,
            116,
            24,
            22
          ]
        ]
      ]
    },
    {
      "name": "10_24.jpeg",
      "detections": [
        [
          "normal",
          0.5565130114555359,
          [
            563,
            203,
            18,
            17
          ]
        ]
      ]
    },
    {
      "name": "4_20.jpeg",
      "detections": [
        [
          "normal",
          0.6298144459724426,
          [
            490,
            502,
            15,
            15
          ]
        ]
      ]
    },
    {
      "name": "61_19.jpeg",
      "detections": [
        [
          "normal",
          0.5602749586105347,
          [
            762,
            741,
            26,
            21
          ]
        ]
      ]
    },
    {
      "name": "15_1.jpeg",
      "detections": [
        [
          "normal",
          0.663793683052063,
          [
            758,
            158,
            42,
            46
          ]
        ]
      ]
    },
    {
      "name": "29_20.jpeg",
      "detections": [
        [
          "normal",
          0.6129250526428223,
          [
            53,
            115,
            21,
            29
          ]
        ]
      ]
    },
    {
      "name": "63_23.jpeg",
      "detections": [
        [
          "normal",
          0.550596296787262,
          [
            62,
            151,
            22,
            18
          ]
        ]
      ]
    },
    {
      "name": "27_21.jpeg",
      "detections": [
        [
          "normal",
          0.6089016199111938,
          [
            142,
            551,
            15,
            18
          ]
        ]
      ]
    },
    {
      "name": "56_19.jpeg",
      "detections": [
        [
          "granular",
          0.5270424485206604,
          [
            254,
            519,
            27,
            33
          ]
        ]
      ]
    },
    {
      "name": "2_18.jpeg",
      "detections": [
        [
          "normal",
          0.5465637445449829,
          [
            765,
            684,
            27,
            24
          ]
        ]
      ]
    },
    {
      "name": "63_2.jpeg",
      "detections": [
        [
          "normal",
          0.6211491227149963,
          [
            544,
            0,
            32,
            30
          ]
        ]
      ]
    },
    {
      "name": "35_18.jpeg",
      "detections": [
        [
          "granular",
          0.5602853298187256,
          [
            610,
            126,
            44,
            31
          ]
        ]
      ]
    },
    {
      "name": "15_0.jpeg",
      "detections": [
        [
          "normal",
          0.5598165392875671,
          [
            629,
            756,
            85,
            44
          ]
        ]
      ]
    },
    {
      "name": "37_20.jpeg",
      "detections": [
        [
          "normal",
          0.5207164883613586,
          [
            181,
            576,
            92,
            136
          ]
        ]
      ]
    },
    {
      "name": "83_17.jpeg",
      "detections": [
        [
          "normal",
          0.5521289110183716,
          [
            402,
            443,
            22,
            26
          ]
        ]
      ]
    },
    {
      "name": "52_20.jpeg",
      "detections": [
        [
          "atypical",
          0.6026650667190552,
          [
            485,
            559,
            43,
            27
          ]
        ],
        [
          "atypical",
          0.597398042678833,
          [
            319,
            307,
            21,
            27
          ]
        ],
        [
          "atypical",
          0.5334952473640442,
          [
            338,
            732,
            24,
            29
          ]
        ]
      ]
    },
    {
      "name": "15_3.jpeg",
      "detections": [
        [
          "normal",
          0.6565245389938354,
          [
            307,
            71,
            37,
            49
          ]
        ]
      ]
    },
    {
      "name": "73_20.jpeg",
      "detections": [
        [
          "atypical",
          0.5462810397148132,
          [
            764,
            513,
            19,
            18
          ]
        ]
      ]
    },
    {
      "name": "57_24.jpeg",
      "detections": [
        [
          "atypical",
          0.5712233781814575,
          [
            615,
            762,
            22,
            20
          ]
        ]
      ]
    },
    {
      "name": "61_13.jpeg",
      "detections": [
        [
          "normal",
          0.6131406426429749,
          [
            241,
            65,
            21,
            20
          ]
        ]
      ]
    },
    {
      "name": "86_19.jpeg",
      "detections": [
        [
          "normal",
          0.6061164736747742,
          [
            123,
            315,
            66,
            51
          ]
        ]
      ]
    }
  ]
}